PathPandemCLI/__init__.py
PathPandemCLI/__main__.py
PathPandemCLI/cli.py
PathPandemCLI/compose_pop.py
PathPandemCLI/db-gen-irwin_hall.py
PathPandemCLI/definitions.py
PathPandemCLI/misc.py
PathPandemCLI/pathogen.py
PathPandemCLI/person.py
PathPandemCLI/plot.py
PathPandemCLI/population.py
PathPandemCLI/reverse_cfr_database.pkl
PathPandemCLI/simul.py
PathPandemCLI/spread_simul.py
PathPandemCLI-0.0.0.1.dev1.data/scripts/PathPandemCLI
PathPandemCLI-0.0.0.1.dev1.dist-info/LICENSE
PathPandemCLI-0.0.0.1.dev1.dist-info/METADATA
PathPandemCLI-0.0.0.1.dev1.dist-info/WHEEL
PathPandemCLI-0.0.0.1.dev1.dist-info/top_level.txt
PathPandemCLI-0.0.0.1.dev1.dist-info/RECORD
