Metadata-Version: 2.1
Name: PathPandemCLI
Version: 0.0.0.1.dev1
Summary: Simulate Pandemic Pathogen Outbreak Non-Gooey version
Home-page: UNKNOWN
Author: Pradyumna Paranjape
Author-email: pradyparanjpe@rediffmail.com
License: GPLv3
Platform: UNKNOWN
Requires-Dist: numpy
Requires-Dist: matplotlib
